dmp3/__init__.py
dmp3/_internal.py
dmp3/dmp3.py
dmp3-0.0.7.dist-info/LICENSE
dmp3-0.0.7.dist-info/METADATA
dmp3-0.0.7.dist-info/WHEEL
dmp3-0.0.7.dist-info/entry_points.txt
dmp3-0.0.7.dist-info/top_level.txt
dmp3-0.0.7.dist-info/RECORD
