Metadata-Version: 2.1
Name: dmp3
Version: 0.0.7
Summary: Download youtube video, playlist, channel. Convert to mp3, store into folder. Efficiently refresh mutiple storage folders.
Author-email: 0xdomyz <septemberwhyms@gmail.com>
Project-URL: homepage, https://github.com/0xdomyz/utube_playlist_mp3_downloader
Project-URL: documentation, https://github.com/0xdomyz/utube_playlist_mp3_downloader
Project-URL: Bug Tracker, https://github.com/0xdomyz/utube_playlist_mp3_downloader/issues
Classifier: Programming Language :: Python :: 3.9
Classifier: Programming Language :: Python :: 3.10
Classifier: Programming Language :: Python :: 3.11
Classifier: License :: OSI Approved :: MIT License
Classifier: Operating System :: Microsoft :: Windows :: Windows 10
Classifier: Operating System :: POSIX :: Linux
Requires-Python: >=3.9
License-File: LICENSE
Requires-Dist: pytube
Requires-Dist: yt-dlp
Requires-Dist: pyyaml
